focal_loss/__init__.py
focal_loss/_binary_focal_loss.py
focal_loss/_categorical_focal_loss.py
focal_loss/utils/__init__.py
focal_loss/utils/validation.py
focal_loss-0.0.7.dist-info/LICENSE
focal_loss-0.0.7.dist-info/METADATA
focal_loss-0.0.7.dist-info/WHEEL
focal_loss-0.0.7.dist-info/top_level.txt
focal_loss-0.0.7.dist-info/RECORD
